Metadata-Version: 1.1
Name: hadapi
Version: 1.0.30
Summary: HAD API Service
Home-page: https://h7f8ovvjxk.execute-api.us-east-1.amazonaws.com/beta/index.html#/
Author: Sensing and Perception Team
Author-email: vladimir.shestak@here.com
License: Property of HERE
Keywords: HAD API model runtime
Platform: UNKNOWN
Classifier: Development Status :: 3 - Alpha
Classifier: Intended Audience :: Developers
Classifier: Topic :: Software Development :: Build Tools
Classifier: License :: OSI Approved :: MIT License
Classifier: Programming Language :: Python :: 2.7
Classifier: Programming Language :: Python :: 3
Classifier: Programming Language :: Python :: 3.3
Classifier: Programming Language :: Python :: 3.4
Classifier: Programming Language :: Python :: 3.5
